RsCmwEvdoMeas/RsCmwEvdoMeas.py
RsCmwEvdoMeas/__init__.py
RsCmwEvdoMeas/enums.py
RsCmwEvdoMeas/repcap.py
RsCmwEvdoMeas/CustomFiles/__init__.py
RsCmwEvdoMeas/CustomFiles/events.py
RsCmwEvdoMeas/CustomFiles/reliability.py
RsCmwEvdoMeas/CustomFiles/utilities.py
RsCmwEvdoMeas/Implementations/Configure.py
RsCmwEvdoMeas/Implementations/MultiEval.py
RsCmwEvdoMeas/Implementations/Oltr.py
RsCmwEvdoMeas/Implementations/Route.py
RsCmwEvdoMeas/Implementations/RpInterval.py
RsCmwEvdoMeas/Implementations/Trigger.py
RsCmwEvdoMeas/Implementations/__init__.py
RsCmwEvdoMeas/Implementations/Configure_/MultiEval.py
RsCmwEvdoMeas/Implementations/Configure_/Oltr.py
RsCmwEvdoMeas/Implementations/Configure_/RfSettings.py
RsCmwEvdoMeas/Implementations/Configure_/__init__.py
RsCmwEvdoMeas/Implementations/Configure_/MultiEval_/Acp.py
RsCmwEvdoMeas/Implementations/Configure_/MultiEval_/Carrier.py
RsCmwEvdoMeas/Implementations/Configure_/MultiEval_/Limit.py
RsCmwEvdoMeas/Implementations/Configure_/MultiEval_/ListPy.py
RsCmwEvdoMeas/Implementations/Configure_/MultiEval_/Result.py
RsCmwEvdoMeas/Implementations/Configure_/MultiEval_/Scount.py
RsCmwEvdoMeas/Implementations/Configure_/MultiEval_/__init__.py
RsCmwEvdoMeas/Implementations/Configure_/MultiEval_/Acp_/Extended.py
RsCmwEvdoMeas/Implementations/Configure_/MultiEval_/Acp_/Foffsets.py
RsCmwEvdoMeas/Implementations/Configure_/MultiEval_/Acp_/Rbw.py
RsCmwEvdoMeas/Implementations/Configure_/MultiEval_/Acp_/__init__.py
RsCmwEvdoMeas/Implementations/Configure_/MultiEval_/Acp_/Extended_/Foffsets.py
RsCmwEvdoMeas/Implementations/Configure_/MultiEval_/Acp_/Extended_/Rbw.py
RsCmwEvdoMeas/Implementations/Configure_/MultiEval_/Acp_/Extended_/__init__.py
RsCmwEvdoMeas/Implementations/Configure_/MultiEval_/Limit_/Acp.py
RsCmwEvdoMeas/Implementations/Configure_/MultiEval_/Limit_/Evm.py
RsCmwEvdoMeas/Implementations/Configure_/MultiEval_/Limit_/Merr.py
RsCmwEvdoMeas/Implementations/Configure_/MultiEval_/Limit_/Obw.py
RsCmwEvdoMeas-3.8.10.5.dist-info/METADATA
RsCmwEvdoMeas-3.8.10.5.dist-info/WHEEL
RsCmwEvdoMeas-3.8.10.5.dist-info/top_level.txt
RsCmwEvdoMeas-3.8.10.5.dist-info/RECORD
